cubicweb_s3storage/__init__.py
cubicweb_s3storage/__pkginfo__.py
cubicweb_s3storage/site_cubicweb.py
cubicweb_s3storage/storages.py
cubicweb_s3storage/testing.py
cubicweb_s3storage/i18n/en.po
cubicweb_s3storage/i18n/es.po
cubicweb_s3storage/i18n/fr.po
cubicweb_s3storage/migration/postcreate.py
cubicweb_s3storage-4.0.2.dist-info/METADATA
cubicweb_s3storage-4.0.2.dist-info/WHEEL
cubicweb_s3storage-4.0.2.dist-info/entry_points.txt
cubicweb_s3storage-4.0.2.dist-info/top_level.txt
cubicweb_s3storage-4.0.2.dist-info/RECORD
