Metadata-Version: 2.4
Name: cubicweb-s3storage
Version: 4.0.2
Summary: A Cubicweb Storage that stores the data on S3
Home-page: https://forge.extranet.logilab.fr/cubicweb/cubes/cubicweb-s3storage
Author: LOGILAB S.A. (Paris, FRANCE)
Author-email: contact@logilab.fr
License: LGPL
Classifier: Environment :: Web Environment
Classifier: Framework :: CubicWeb
Classifier: Programming Language :: Python
Classifier: Programming Language :: JavaScript
Requires-Dist: cubicweb<5.0.0,>=4.0.0
Requires-Dist: boto3<1.36.0
Dynamic: author
Dynamic: author-email
Dynamic: classifier
Dynamic: description
Dynamic: home-page
Dynamic: license
Dynamic: requires-dist
Dynamic: summary
